entra/__init__.py
entra/_version.py
entra/caped.yaml
entra/covariance_minimizer.py
entra/dataframe_transformer.py
entra/effective_basis.py
entra/scalar_basis.py
entra/tensor_basis.py
entra/transformation.py
entra/utils.py
entra/vector_sampler.py
entra/_tests/__init__.py
entra/_tests/test_divergence.py
entra/_tests/test_scalar_basis.py
entra/_tests/test_tensor_basis.py
entra/_tests/test_vector_sampler.py
entra-0.4.0.dist-info/licenses/LICENSE
entra-0.4.0.dist-info/METADATA
entra-0.4.0.dist-info/WHEEL
entra-0.4.0.dist-info/entry_points.txt
entra-0.4.0.dist-info/top_level.txt
entra-0.4.0.dist-info/RECORD
